setup.py
smallutils/__init__.py
smallutils/notepad_data_input.py
smallutils/start_prgm_handler.py
smallutils/tinyutils.py
smallutils.egg-info/PKG-INFO
smallutils.egg-info/SOURCES.txt
smallutils.egg-info/dependency_links.txt
smallutils.egg-info/not-zip-safe
smallutils.egg-info/requires.txt
smallutils.egg-info/top_level.txt