Metadata-Version: 1.0
Name: smallutils
Version: 0.1.3
Summary: Collection of small utils
Home-page: https://github.com/spidezad/smallutils
Author: Tan Kok Hua
Author-email: kokhua81@gmail.com
License: UNKNOWN
Platform: UNKNOWN
